mpi_map/__init__.py
mpi_map/_version.py
mpi_map/misc.py
mpi_map/tests/__init__.py
mpi_map/tests/test_all.py
mpi_map/tests/test_big_bcast.py
mpi_map/tests/test_pool.py
mpi_map-2.6.data/scripts/mpi_eval.py
mpi_map-2.6.data/scripts/mpi_eval_method.py
mpi_map-2.6.data/scripts/mpi_pool_v1.py
mpi_map-2.6.data/scripts/mpi_pool_v2.py
mpi_map-2.6.dist-info/COPYING
mpi_map-2.6.dist-info/COPYING.LESSER
mpi_map-2.6.dist-info/METADATA
mpi_map-2.6.dist-info/WHEEL
mpi_map-2.6.dist-info/pbr.json
mpi_map-2.6.dist-info/top_level.txt
mpi_map-2.6.dist-info/RECORD
