Metadata-Version: 2.1
Name: mpi-map
Version: 2.6
Summary: Tools running parallel processes
Home-page: http://www2.compute.dtu.dk/~dabi/
Author: Daniele Bigoni
Author-email: dabi@dtu.dk
License: COPYING.LESSER
Platform: UNKNOWN
Requires-Dist: mpi4py
Requires-Dist: dill
